recx/__init__.py
recx/checks.py
recx/exceptions.py
recx/rec.py
recx/results.py
recx-0.0.8.dist-info/WHEEL
recx-0.0.8.dist-info/METADATA
recx-0.0.8.dist-info/RECORD
