Metadata-Version: 2.4
Name: recx
Version: 0.0.8
Summary: Lightweight reconciliation tests for DataFrames
Author: Adrian Letchford
Author-email: Adrian Letchford <me@dradrian.com>
License-Expression: MIT
Requires-Dist: pandas>=2.2.0
Requires-Python: >=3.10
Project-URL: Documentation, https://recx.readthedocs.io
Project-URL: Homepage, https://github.com/robolyst/recx
Project-URL: Issues, https://github.com/robolyst/recx/issues
Project-URL: Source, https://github.com/robolyst/recx
